pymorse/__init__.py
pymorse/morse.py
pymorse2-0.0.2.dist-info/DESCRIPTION.rst
pymorse2-0.0.2.dist-info/METADATA
pymorse2-0.0.2.dist-info/RECORD
pymorse2-0.0.2.dist-info/WHEEL
pymorse2-0.0.2.dist-info/metadata.json
pymorse2-0.0.2.dist-info/top_level.txt
